sunpy_sphinx_theme/__init__.py
sunpy_sphinx_theme/cards.py
sunpy_sphinx_theme/conf.py
sunpy_sphinx_theme/theme/sunpy/theme.conf
sunpy_sphinx_theme/theme/sunpy/components/built-with.html
sunpy_sphinx_theme/theme/sunpy/components/footer-links.html
sunpy_sphinx_theme/theme/sunpy/components/navbar-logo.html
sunpy_sphinx_theme/theme/sunpy/components/navbar_center.html
sunpy_sphinx_theme/theme/sunpy/components/navbar_start.html
sunpy_sphinx_theme/theme/sunpy/components/sst-sidebar-nav.html
sunpy_sphinx_theme/theme/sunpy/sections/header.html
sunpy_sphinx_theme/theme/sunpy/static/sunpy_style.css
sunpy_sphinx_theme/theme/sunpy/static/css/rtd_enhanced_search.css
sunpy_sphinx_theme/theme/sunpy/static/css/sunpy_cards.css
sunpy_sphinx_theme/theme/sunpy/static/img/favicon-32.ico
sunpy_sphinx_theme/theme/sunpy/static/img/sunpy_icon.svg
sunpy_sphinx_theme/theme/sunpy/static/img/sunpy_icon_128x128.png
sunpy_sphinx_theme/theme/sunpy/static/js/rtd_enhanced_search.js
sunpy_sphinx_theme/theme/sunpy/static/js/submenu-concertina-toggle.js
sunpy_sphinx_theme-2.1.0.dist-info/licenses/LICENSE.md
sunpy_sphinx_theme-2.1.0.dist-info/METADATA
sunpy_sphinx_theme-2.1.0.dist-info/WHEEL
sunpy_sphinx_theme-2.1.0.dist-info/entry_points.txt
sunpy_sphinx_theme-2.1.0.dist-info/top_level.txt
sunpy_sphinx_theme-2.1.0.dist-info/RECORD
